netbox_librenms_plugin/__init__.py
netbox_librenms_plugin/admin.py
netbox_librenms_plugin/filters.py
netbox_librenms_plugin/filtersets.py
netbox_librenms_plugin/forms.py
netbox_librenms_plugin/import_utils.py
netbox_librenms_plugin/import_validation_helpers.py
netbox_librenms_plugin/jobs.py
netbox_librenms_plugin/librenms_api.py
netbox_librenms_plugin/models.py
netbox_librenms_plugin/navigation.py
netbox_librenms_plugin/urls.py
netbox_librenms_plugin/utils.py
netbox_librenms_plugin/api/__init__.py
netbox_librenms_plugin/api/serializers.py
netbox_librenms_plugin/api/urls.py
netbox_librenms_plugin/api/views.py
netbox_librenms_plugin/migrations/0001_initial.py
netbox_librenms_plugin/migrations/0002_interfacetypemapping_created_and_more.py
netbox_librenms_plugin/migrations/0003_interfacetypemapping_librenms_speed_and_more.py
netbox_librenms_plugin/migrations/0004_librenmssettings.py
netbox_librenms_plugin/migrations/0005_remove_librenmssettings_created_and_more.py
netbox_librenms_plugin/migrations/0006_interfacetypemapping_description.py
netbox_librenms_plugin/migrations/0007_librenmssettings_vc_member_name_pattern.py
netbox_librenms_plugin/migrations/0008_librenmssettings_import_defaults.py
netbox_librenms_plugin/migrations/__init__.py
netbox_librenms_plugin/static/netbox_librenms_plugin/js/librenms_import.js
netbox_librenms_plugin/static/netbox_librenms_plugin/js/librenms_sync.js
netbox_librenms_plugin/tables/VM_status.py
netbox_librenms_plugin/tables/__init__.py
netbox_librenms_plugin/tables/cables.py
netbox_librenms_plugin/tables/device_status.py
netbox_librenms_plugin/tables/interfaces.py
netbox_librenms_plugin/tables/ipaddresses.py
netbox_librenms_plugin/tables/locations.py
netbox_librenms_plugin/tables/mappings.py
netbox_librenms_plugin/templates/netbox_librenms_plugin/_cable_sync.html
netbox_librenms_plugin/templates/netbox_librenms_plugin/_cable_sync_content.html
netbox_librenms_plugin/templates/netbox_librenms_plugin/_interface_sync.html
netbox_librenms_plugin-0.4.2.dist-info/licenses/LICENSE
netbox_librenms_plugin-0.4.2.dist-info/METADATA
netbox_librenms_plugin-0.4.2.dist-info/WHEEL
netbox_librenms_plugin-0.4.2.dist-info/top_level.txt
netbox_librenms_plugin-0.4.2.dist-info/RECORD
