Metadata-Version: 2.4
Name: netbox-librenms-plugin
Version: 0.4.2
Summary: Netbox plugin to sync data between LibreNMS and Netbox.
Author: Andy Norwood
Classifier: Development Status :: 3 - Alpha
Classifier: Intended Audience :: Developers
Classifier: Natural Language :: English
Classifier: Programming Language :: Python :: 3 :: Only
Classifier: Programming Language :: Python :: 3.10
Classifier: Programming Language :: Python :: 3.11
Classifier: Programming Language :: Python :: 3.12
Requires-Python: >=3.10.0
License-File: LICENSE
Dynamic: license-file
